diutil/__init__.py
diutil/customOperatorTemplate.py
diutil/gensolution.py
diutil/textfield_parser.py
gensolution-0.0.14.dist-info/LICENSE
gensolution-0.0.14.dist-info/METADATA
gensolution-0.0.14.dist-info/WHEEL
gensolution-0.0.14.dist-info/entry_points.txt
gensolution-0.0.14.dist-info/top_level.txt
gensolution-0.0.14.dist-info/RECORD
