Metadata-Version: 2.1
Name: gensolution
Version: 0.0.14
Summary: Generates solution package when locally developing SAP DI operators
Home-page: https://github.com/thhapke/gensolution
Author: Thorsten Hapke
Author-email: thorsten.hapke@sap.com
License: UNKNOWN
Keywords: SAP Data Intelligence,genjson
Platform: UNKNOWN
Classifier: Programming Language :: Python :: 3.5
Classifier: Programming Language :: Python :: 3.6
Classifier: Programming Language :: Python :: 3.7
Classifier: License :: OSI Approved :: MIT License
Classifier: Operating System :: OS Independent
